{
  "id": "taskwarrior",
  "name": "Taskwarrior",
  "description": "Show pending Taskwarrior tasks sorted by urgency",
  "category": "utilities",
  "repo": "https://github.com/cyrylas/dms-taskwarrior",
  "author": "Michał Wazgird",
  "capabilities": ["dankbar-widget"],
  "dependencies": ["taskwarrior"],
  "compositors": ["hyprland", "niri", "sway"],
  "distro": ["any"],
  "screenshot": "https://raw.githubusercontent.com/cyrylas/dms-taskwarrior/master/screenshots/screenshot-dark.png",
  "requires_dms": ">=1.2.0"
}
