{
    "id": "dankscale",
    "name": "Dankscale",
    "capabilities": ["dankbar-widget", "control-center", "vpn", "network"],
    "category": "utilities",
    "repo": "https://github.com/dwright134/dms-dankscale",
    "author": "dwright",
    "description": "Manage your Tailscale network: connect/disconnect, switch accounts, copy device IPs, pick exit nodes, manage routes, and control DNS",
    "dependencies": ["tailscale"],
    "compositors": ["any"],
    "distro": ["any"],
    "screenshot": "https://raw.githubusercontent.com/dwright134/dms-dankscale/main/docs/screenshot.png"
}
