{
  "level": "fail",
  "dark": {
    "level": "fail",
    "minRatio": 3.63,
    "worstPair": [
      "surfaceVariantText",
      "surfaceContainerHigh"
    ],
    "nonText": {
      "minRatio": 3.64,
      "worstPair": [
        "error",
        "surfaceContainer"
      ]
    },
    "variants": {
      "blue": "fail",
      "green": "fail",
      "pink": "fail"
    }
  },
  "light": {
    "level": "fail",
    "minRatio": 2.26,
    "worstPair": [
      "primary",
      "surfaceContainer"
    ],
    "nonText": {
      "minRatio": 2.89,
      "worstPair": [
        "error",
        "surfaceContainer"
      ]
    },
    "variants": {
      "blue": "fail",
      "green": "fail",
      "pink": "fail"
    }
  }
}
